CHANGES.rst
CONTRIBUTORS.rst
MANIFEST.in
README.rst
setup.py
src/mls/__init__.py
src/mls.fabfile.egg-info/PKG-INFO
src/mls.fabfile.egg-info/SOURCES.txt
src/mls.fabfile.egg-info/dependency_links.txt
src/mls.fabfile.egg-info/entry_points.txt
src/mls.fabfile.egg-info/namespace_packages.txt
src/mls.fabfile.egg-info/not-zip-safe
src/mls.fabfile.egg-info/requires.txt
src/mls.fabfile.egg-info/top_level.txt
src/mls/fabfile/__init__.py
src/mls/fabfile/bootstrap.py
src/mls/fabfile/client.py
src/mls/fabfile/database.py
src/mls/fabfile/frontend.py
src/mls/fabfile/roles.py
src/mls/fabfile/utils.py
src/mls/fabfile/examples/fabfile.py
src/mls/fabfile/examples/.chef/knife.rb