Metadata-Version: 1.1
Name: mls.fabfile
Version: 0.3
Summary: Deploy and manage Propertyshelf MLS applications using Fabric.
Home-page: https://github.com/propertyshelf/mls.fabfile
Author: Propertyshelf, Inc.
Author-email: development@propertyshelf.com
License: BSD
Download-URL: http://pypi.python.org/pypi/mls.fabfile
Keywords: fabric python mls deployment
Platform: UNKNOWN
Classifier: Programming Language :: Python
